fal_mcp_server/__init__.py
fal_mcp_server/model_registry.py
fal_mcp_server/server.py
fal_mcp_server/server_backup.py
fal_mcp_server/server_dual.py
fal_mcp_server/server_http.py
fal_mcp_server/handlers/__init__.py
fal_mcp_server/handlers/audio_handlers.py
fal_mcp_server/handlers/image_editing_handlers.py
fal_mcp_server/handlers/image_handlers.py
fal_mcp_server/handlers/utility_handlers.py
fal_mcp_server/handlers/video_handlers.py
fal_mcp_server/queue/__init__.py
fal_mcp_server/queue/base.py
fal_mcp_server/queue/handle_get.py
fal_mcp_server/queue/polling.py
fal_mcp_server/queue/subscribe.py
fal_mcp_server/tools/__init__.py
fal_mcp_server/tools/audio_tools.py
fal_mcp_server/tools/image_editing_tools.py
fal_mcp_server/tools/image_tools.py
fal_mcp_server/tools/utility_tools.py
fal_mcp_server/tools/video_tools.py
fal_mcp_server-1.18.0.dist-info/METADATA
fal_mcp_server-1.18.0.dist-info/WHEEL
fal_mcp_server-1.18.0.dist-info/entry_points.txt
fal_mcp_server-1.18.0.dist-info/licenses/LICENSE
fal_mcp_server-1.18.0.dist-info/RECORD
