Metadata-Version: 2.4
Name: fal-mcp-server
Version: 1.18.0
Summary: MCP server for Fal.ai - Generate images, videos, music and audio with AI models
Project-URL: homepage, https://github.com/raveenb/fal-mcp-server
Project-URL: repository, https://github.com/raveenb/fal-mcp-server
Project-URL: issues, https://github.com/raveenb/fal-mcp-server/issues
License: MIT
License-File: LICENSE
Keywords: ai,claude,fal,image-generation,llm,mcp
Classifier: Development Status :: 4 - Beta
Classifier: Intended Audience :: Developers
Classifier: License :: OSI Approved :: MIT License
Classifier: Programming Language :: Python :: 3
Classifier: Programming Language :: Python :: 3.10
Classifier: Programming Language :: Python :: 3.11
Classifier: Programming Language :: Python :: 3.12
Requires-Python: >=3.10
Requires-Dist: fal-client>=0.5.0
Requires-Dist: httpx>=0.27.0
Requires-Dist: loguru>=0.7.0
Requires-Dist: mcp>=1.6.0
Requires-Dist: pillow>=10.0.0
Requires-Dist: sse-starlette>=2.0.0
Requires-Dist: starlette>=0.40.0
Requires-Dist: uvicorn>=0.34.0
Provides-Extra: dev
Requires-Dist: black>=24.0.0; extra == 'dev'
Requires-Dist: mypy>=1.13.0; extra == 'dev'
Requires-Dist: pytest-asyncio>=0.24.0; extra == 'dev'
Requires-Dist: pytest-cov>=6.0.0; extra == 'dev'
Requires-Dist: pytest>=8.0.0; extra == 'dev'
Requires-Dist: pyyaml>=6.0.0; extra == 'dev'
Requires-Dist: requests>=2.32.0; extra == 'dev'
Requires-Dist: ruff>=0.8.0; extra == 'dev'
Requires-Dist: types-aiofiles>=24.0.0; extra == 'dev'
